dictionary/__init__.py
dictionary/dictionary.py
cs453_hw1_elif_ozer-3.0.0.dist-info/METADATA
cs453_hw1_elif_ozer-3.0.0.dist-info/WHEEL
cs453_hw1_elif_ozer-3.0.0.dist-info/top_level.txt
cs453_hw1_elif_ozer-3.0.0.dist-info/RECORD
