Metadata-Version: 2.1
Name: cs453-hw1-elif-ozer
Version: 3.0.0
Summary: UNKNOWN
Author: Elif Ozer
License: UNKNOWN
Platform: UNKNOWN
Requires-Python: >=3.8
Requires-Dist: requests (>=2.23.0)
